ssi_bridge/__init__.py
ssi_bridge/client.py
ssi_bridge/ssi_dummies.py
ssi_bridge/util.py
ssi_bridge/ssi_dummy/__init__.py
ssi_bridge/ssi_dummy/ssi_receiver_dummy.py
ssi_bridge/ssi_dummy/ssi_sender_dummy.py
ssi_bridge/transformers/__init__.py
ssi_bridge/transformers/loggers.py
ssi_bridge-0.0.5.dist-info/LICENSE
ssi_bridge-0.0.5.dist-info/METADATA
ssi_bridge-0.0.5.dist-info/WHEEL
ssi_bridge-0.0.5.dist-info/top_level.txt
ssi_bridge-0.0.5.dist-info/RECORD
