Metadata-Version: 2.1
Name: ssi-bridge
Version: 0.0.5
Summary: Connection module for the Social Signal Interpretation framework. Alpha Version.
Home-page: UNKNOWN
Author: Silvan Mertes
License: UNKNOWN
Platform: UNKNOWN
Classifier: Programming Language :: Python :: 3
Classifier: License :: OSI Approved :: GNU General Public License v3 (GPLv3)
Classifier: Operating System :: OS Independent
Requires-Python: >=2.7
